pinggy/__init__.py
pinggy/core.py
pinggy/pylib.py
pinggy/bin/libpinggy.so
pinggy/bin/pinggyclient
dev_pinggy-1.0.0.dist-info/METADATA
dev_pinggy-1.0.0.dist-info/WHEEL
dev_pinggy-1.0.0.dist-info/top_level.txt
dev_pinggy-1.0.0.dist-info/RECORD
