Metadata-Version: 2.1
Name: dev-pinggy
Version: 1.0.0
Summary: Pinggy package for tunneling
Home-page: UNKNOWN
Author: Bishnu
Author-email: bishnuthakur284@gmail.com
License: UNKNOWN
Platform: UNKNOWN
Classifier: Programming Language :: Python :: 3
Classifier: Operating System :: OS Independent
Requires-Python: >=3.6
